{"assets/icons/chat.svg":["assets/icons/chat.svg"],"assets/icons/facebook.svg":["assets/icons/facebook.svg"],"assets/icons/google-plus.svg":["assets/icons/google-plus.svg"],"assets/icons/login.svg":["assets/icons/login.svg"],"assets/icons/signup.svg":["assets/icons/signup.svg"],"assets/icons/twitter.svg":["assets/icons/twitter.svg"],"assets/images/.DS_Store":["assets/images/.DS_Store"],"assets/images/login_bottom.png":["assets/images/login_bottom.png"],"assets/images/main_bottom.png":["assets/images/main_bottom.png"],"assets/images/main_top.png":["assets/images/main_top.png"],"assets/images/qr.JPG":["assets/images/qr.JPG"],"assets/images/signup_top.png":["assets/images/signup_top.png"],"assets/images/su%20copy.png":["assets/images/su%20copy.png"],"assets/images/su.png":["assets/images/su.png"],"assets/images/su1.png":["assets/images/su1.png"],"assets/images/su10.png":["assets/images/su10.png"],"assets/images/su2.png":["assets/images/su2.png"],"assets/images/su3.png":["assets/images/su3.png"],"assets/images/su4.png":["assets/images/su4.png"],"assets/images/su5.png":["assets/images/su5.png"],"assets/images/su6.png":["assets/images/su6.png"],"assets/images/su7.png":["assets/images/su7.png"],"assets/images/su8.png":["assets/images/su8.png"],"assets/images/su9.png":["assets/images/su9.png"],"packages/cupertino_icons/assets/CupertinoIcons.ttf":["packages/cupertino_icons/assets/CupertinoIcons.ttf"]}